malaya_boilerplate/__init__.py
malaya_boilerplate/backblaze.py
malaya_boilerplate/execute.py
malaya_boilerplate/frozen_graph.py
malaya_boilerplate/hparams.py
malaya_boilerplate/huggingface.py
malaya_boilerplate/saved_model.py
malaya_boilerplate/torch_utils.py
malaya_boilerplate/utils.py
malaya_boilerplate/train/__init__.py
malaya_boilerplate/train/activation.py
malaya_boilerplate/train/config.py
malaya_boilerplate/train/loss.py
malaya_boilerplate/train/prepare_data.py
malaya_boilerplate/train/schedule.py
malaya_boilerplate/train/utils.py
malaya_boilerplate/train/optimizer/__init__.py
malaya_boilerplate/train/optimizer/adamw.py
malaya_boilerplate/train/optimizer/adamw_tf2.py
malaya_boilerplate/train/optimizer/gradient.py
malaya_boilerplate-0.0.24.dist-info/LICENSE
malaya_boilerplate-0.0.24.dist-info/METADATA
malaya_boilerplate-0.0.24.dist-info/WHEEL
malaya_boilerplate-0.0.24.dist-info/top_level.txt
malaya_boilerplate-0.0.24.dist-info/RECORD
