Metadata-Version: 2.1
Name: malaya-boilerplate
Version: 0.0.24
Summary: Tensorflow freeze graph optimization and boilerplates to share among Malaya projects.
Home-page: https://github.com/huseinzol05/malaya-boilerplate
Download-URL: https://github.com/huseinzol05/malaya-boilerplate/archive/master.zip
Author: huseinzol05
Author-email: husein.zol05@gmail.com
License: MIT
Keywords: nlp,bm
Classifier: Programming Language :: Python :: 3.6
Classifier: Intended Audience :: Developers
Classifier: License :: OSI Approved :: MIT License
Classifier: Operating System :: OS Independent
Requires-Python: >=3.6
License-File: LICENSE
Requires-Dist: tqdm
Requires-Dist: requests
Requires-Dist: huggingface-hub
